{
  "journee": 1,
  "date": "08-09 novembre 2025",
  "equipes": {
    "u18a": {
      "matches": [
        {
          "date": "08/11/2025",
          "heure": "9h30",
          "adversaire": "GJ Goulaine U18",
          "lieu": "Exterieur",
          "responsables": {
            "maillots": ["Baptiste"],
            "voitures": ["Théo", "Germain","Enri","Lucas" ],
            "bar": []
          },
          "convocation": [
            { "nom": "Valentin" },
            { "nom": "Clement" },
            { "nom": "Germain" },
            { "nom": "Flavien" },
            { "nom": "Enri" },
            { "nom": "Théo" },
            { "nom": "Baptiste" },
            { "nom": "Lucas" },
            { "nom": "Alexis" },
            { "nom": "Roman" },
            { "nom": "Kyllian" },
            { "nom": "Elouen" },
            { "nom": "Eliott" },
            { "nom": "Antonin LEMAITRE" }
          ]
        }
      ]
    },
    "u18b": {
      "matches": [
        {
          "date": "13/11/2025",
          "heure": "15h30",
          "adversaire": "Grenoble U18",
          "lieu": "Extérieur",
          "responsables": {
            "maillots": ["Robert"],
            "voitures": ["Lambert", "Fontaine"],
            "bar": ["Perrin", "Bonnet"]
          },
          "convocation": [
            {"nom": "Robert"},
            {"nom": "Lambert"},
            {"nom": "Fontaine"},
            {"nom": "Perrin"},
            {"nom": "Bonnet"},
            {"nom": "Lemoine"},
            {"nom": "Boyer"},
            {"nom": "Renaud"},
            {"nom": "Gauthier"},
            {"nom": "Collet"},
            {"nom": "Descamps"},
            {"nom": "Gaillard"},
            {"nom": "Vincent"},
            {"nom": "Picard"}
          ]
        }
      ]
    },
    "u16a": {
      "matches": [
        {
          "date": "14/11/2025",
          "heure": "16h00",
          "adversaire": "Clermont U16",
          "lieu": "Domicile",
          "responsables": {
            "maillots": ["Carpentier"],
            "voitures": ["Renard", "Chevalier"],
            "bar": ["Lucas", "Moulin"]
          },
          "convocation": [
            {"nom": "Carpentier"},
            {"nom": "Renard"},
            {"nom": "Chevalier"},
            {"nom": "Lucas"},
            {"nom": "Moulin"},
            {"nom": "Perrot"},
            {"nom": "Lamy"},
            {"nom": "Aubert"},
            {"nom": "Guichard"},
            {"nom": "Leclerc"},
            {"nom": "Masson"},
            {"nom": "Parent"},
            {"nom": "Giraud"},
            {"nom": "Boucher"}
          ]
        }
      ]
    }
  }
}
