{
  "journee": 1,
  "date": "12-14 novembre 2025",
  "equipes": {
    "u18a": {
      "matches": [
        {
          "date": "12/11/2025",
          "heure": "14h00",
          "adversaire": "Lyon U18",
          "lieu": "Domicile",
          "responsables": {
            "maillots": ["Dupont"],
            "voitures": ["Martin", "Durand"],
            "bar": ["Bernard", "Petit"]
          },
          "convocation": [
            {"nom": "Dupont"},
            {"nom": "Martin"},
            {"nom": "Durand"},
            {"nom": "Bernard"},
            {"nom": "Petit"},
            {"nom": "Roux"},
            {"nom": "Morel"},
            {"nom": "Simon"},
            {"nom": "Lefevre"},
            {"nom": "Girard"},
            {"nom": "Marchand"},
            {"nom": "Fabre"},
            {"nom": "Lopez"},
            {"nom": "Blanc"}
          ]
        }
      ]
    },
    "u18b": {
      "matches": [
        {
          "date": "13/11/2025",
          "heure": "15h30",
          "adversaire": "Grenoble U18",
          "lieu": "Extérieur",
          "responsables": {
            "maillots": ["Robert"],
            "voitures": ["Lambert", "Fontaine"],
            "bar": ["Perrin", "Bonnet"]
          },
          "convocation": [
            {"nom": "Robert"},
            {"nom": "Lambert"},
            {"nom": "Fontaine"},
            {"nom": "Perrin"},
            {"nom": "Bonnet"},
            {"nom": "Lemoine"},
            {"nom": "Boyer"},
            {"nom": "Renaud"},
            {"nom": "Gauthier"},
            {"nom": "Collet"},
            {"nom": "Descamps"},
            {"nom": "Gaillard"},
            {"nom": "Vincent"},
            {"nom": "Picard"}
          ]
        }
      ]
    },
    "u16a": {
      "matches": [
        {
          "date": "14/11/2025",
          "heure": "16h00",
          "adversaire": "Clermont U16",
          "lieu": "Domicile",
          "responsables": {
            "maillots": ["Carpentier"],
            "voitures": ["Renard", "Chevalier"],
            "bar": ["Lucas", "Moulin"]
          },
          "convocation": [
            {"nom": "Carpentier"},
            {"nom": "Renard"},
            {"nom": "Chevalier"},
            {"nom": "Lucas"},
            {"nom": "Moulin"},
            {"nom": "Perrot"},
            {"nom": "Lamy"},
            {"nom": "Aubert"},
            {"nom": "Guichard"},
            {"nom": "Leclerc"},
            {"nom": "Masson"},
            {"nom": "Parent"},
            {"nom": "Giraud"},
            {"nom": "Boucher"}
          ]
        }
      ]
    }
  }
}
